Topsis_AbhishekVohra_102003439/102003439.py
Topsis_AbhishekVohra_102003439/AbhishekVohra_102003439.py
Topsis_AbhishekVohra_102003439-1.3.dist-info/License.txt
Topsis_AbhishekVohra_102003439-1.3.dist-info/METADATA
Topsis_AbhishekVohra_102003439-1.3.dist-info/WHEEL
Topsis_AbhishekVohra_102003439-1.3.dist-info/entry_points.txt
Topsis_AbhishekVohra_102003439-1.3.dist-info/top_level.txt
Topsis_AbhishekVohra_102003439-1.3.dist-info/RECORD
