Metadata-Version: 2.1
Name: Topsis-AbhishekVohra-102003439
Version: 1.3
Summary: Doing Evaluation of alternatives based on multiple criteria using TOPSIS method.
Home-page: UNKNOWN
Author: Abhishek Vohra
Author-email: avohra_be20@thapar.edu
License: UNKNOWN
Platform: UNKNOWN
Classifier: Programming Language :: Python :: 3
Classifier: License :: OSI Approved :: MIT License
Classifier: Operating System :: OS Independent
License-File: License.txt
Requires-Dist: pandas
